pylint_secure_coding_standard.py
pylint_secure_coding_standard-1.5.1.dist-info/LICENSE
pylint_secure_coding_standard-1.5.1.dist-info/METADATA
pylint_secure_coding_standard-1.5.1.dist-info/WHEEL
pylint_secure_coding_standard-1.5.1.dist-info/top_level.txt
pylint_secure_coding_standard-1.5.1.dist-info/RECORD
