Metadata-Version: 2.1
Name: pylint-secure-coding-standard
Version: 1.5.1
Summary: Pylint plugin adding some checks to make Python code adhere to more secure coding standard
Home-page: https://github.com/Takishima/pylint-secure-coding-standard
Author: Damien Nguyen
Author-email: ngn.damien@gmail.com
License: Apache2
Classifier: Environment :: Console
Classifier: Intended Audience :: Developers
Classifier: License :: OSI Approved :: Apache Software License
Classifier: Natural Language :: English
Classifier: Programming Language :: Python :: 3
Classifier: Programming Language :: Python :: 3 :: Only
Classifier: Programming Language :: Python :: 3.8
Classifier: Programming Language :: Python :: 3.9
Classifier: Programming Language :: Python :: 3.10
Classifier: Programming Language :: Python :: 3.11
Requires-Python: >=3.8
License-File: LICENSE
Requires-Dist: pylint>=3.0
Provides-Extra: test
Requires-Dist: mock; extra == "test"
Requires-Dist: pytest; extra == "test"
Requires-Dist: pytest-cov; extra == "test"
Requires-Dist: pytest-mock; extra == "test"
